Workbook
Name BrowseRecords: RiskSerializationData8!$6:$7
Name DistributionRecords: RiskSerializationData8!$10:$13
Name SerializationHeader: RiskSerializationData8!$A$1:$B$3

Sheet Principal
B1: MINERA FINE COPPER
B2: Las celdas en azul corresponden a datos de entrada.
B4: SUPUESTOS | H4: RESULTADOS
B6: Costo de Oportunidad de Capital | E6: Aspectos Comerciales | H6: Cok | I6: =+C7 -> 0.12
B7: Cok | C7: 0.12 | E7: Precio Venta (US$/Tn) | F7: 4550
H8: Escenario Base
B9: Inversiones en millones US$ | E9: Año Operación 1 | F9: 0.25 | H9: VAN | I9: =+NPV(I6,'Flujos Esc Base'!D55:I55)+'Flujos Esc Base'!C55 -> -214.99895
B10: Terreno | C10: 15 | E10: Año Operación 2 | F10: 0.25
B11: Equipos | C11: 150 | E11: Año Operación 3 | F11: 0.25 | H11: Escenario con Etapas de Exploración y Explotación
E12: Año Operación 4 | F12: 0.25 | H12: VAN | I12: =+NPV(I6,'Flujos con Etapas'!D56:K56)+'Flujos con Etapas'!C56 -> 35.540822
B13: Restauración_Terreno | C13: 5
E14: Aspectos Producción
B15: Valor Residual de Inversiones | E15: Volumen Reservas (Tn) | F15: 850000
B16: Valor Mercado Equipos | C16: 75
B17: Valor Terreno (US$ MM) | C17: 20 | E17: Costos
E18: Costo Variable (US$/Tn) | F18: 1980
B19: Inv Exploración y Factibilidad | E19: Costo Fijo (US$ MM) | F19: 500
B20: Año 1 (US$ MM) | C20: 10
B21: Año 2 (US$ MM) | C21: 10
C22: =+SUM(C20:C21) -> 20

Sheet rsklibSimData
