Workbook

Sheet Principal
B1: MINERA FINE COPPER
B2: Las celdas en azul corresponden a datos de entrada.
B4: SUPUESTOS | H4: RESULTADOS
B6: Costo de Oportunidad de Capital | E6: Aspectos Comerciales | H6: Cok | I6: =+C7 -> 0.12
B7: Cok | C7: 0.12 | E7: Precio Venta (US$/Tn) | F7: 4550
H8: Escenario Base
B9: Inversiones en millones US$ | E9: Año Operación 1 | F9: 0.25 | H9: VAN | I9: =+NPV(I6,'Flujos Esc Base'!D55:I55)+'Flujos Esc Base'!C55 -> 30.057083
B10: Terreno | C10: 15 | E10: Año Operación 2 | F10: 0.25
B11: Equipos | C11: 150 | E11: Año Operación 3 | F11: 0.25 | H11: Escenario con Etapas de Exploración y Explotación
E12: Año Operación 4 | F12: 0.25 | H12: VAN | I12: =+NPV(I6,'Flujos con Etapas'!D56:K56)+'Flujos con Etapas'!C56 -> 4.0187202
B13: Restauración_Terreno | C13: 5
E14: Aspectos Producción
B15: Valor Residual de Inversiones | E15: Volumen Reservas (Tn) | F15: 850000
B16: Valor Mercado Equipos | C16: 75
B17: Valor Terreno (US$ MM) | C17: 20 | E17: Costos
E18: Costo Variable (US$/Tn) | F18: 1980
B19: Inv Exploración y Factibilidad | E19: Costo Fijo (US$ MM) | F19: 500
B20: Año 1 (US$ MM) | C20: 10
B21: Año 2 (US$ MM) | C21: 10
C22: =+SUM(C20:C21) -> 20

Sheet Flujos Esc Base
B2: I. INVERSIONES
B4: Valor Mercado | C4: US$ MM
B5: Terreno | C5: =+Principal!C17 -> 20
B6: Equipos | C6: =+Principal!C16 -> 75
B8: FCI (US$ MM) | C8: 0 | D8: 1 | E8: 2 | F8: 3 | G8: 4 | H8: 5 | I8: 6
B9: Terreno | C9: =-Principal!C10 -> -15
B10: Equipo | C10: =-Principal!C11 -> -150 | G10: =C6 -> 75
B11: Restauración_Terreno | H11: =-Principal!C13 -> -5
B12: Valor Venta Terreno | I12: =+C5 -> 20
B13: F. Inversiones | C13: =+SUM(C9:C12) -> -165 | D13: =+SUM(D9:D12) -> 0 | E13: =+SUM(E9:E12) -> 0 | F13: =+SUM(F9:F12) -> 0 | G13: =+SUM(G9:G12) -> 75 | H13: =+SUM(H9:H12) -> -5 | I13: =+SUM(I9:I12) -> 20
B15: II. PRODUCCIÓN
B17: Volumen Reservas | C17: =+Principal!F15 -> 850000
C20: 0 | D20: 1 | E20: 2 | F20: 3 | G20: 4
B21: % Mineral vendido | D21: =+Principal!$F$9 -> 0.25 | E21: =+Principal!$F$10 -> 0.25 | F21: =+Principal!$F$11 -> 0.25 | G21: =+Principal!$F$12 -> 0.25
B22: Producción (Tn) | D22: =+D21*$C$17 -> 212500 | E22: =+E21*$C$17 -> 212500 | F22: =+F21*$C$17 -> 212500 | G22: =+G21*$C$17 -> 212500
B24: III. INGRESOS
B26: Ingresos (US$ MM) | C26: 0 | D26: 1 | E26: 2 | F26: 3 | G26: 4
B27: Precio (US$/Tn) | C27: =+Principal!$F$7 -> 4550 | D27: =+Principal!$F$7 -> 4550 | E27: =+Principal!$F$7 -> 4550 | F27: =+Principal!$F$7 -> 4550 | G27: =+Principal!$F$7 -> 4550
B28: Total Ingresos | D28: =+D22*D27/1000000 -> 966.875 | E28: =+E22*E27/1000000 -> 966.875 | F28: =+F22*F27/1000000 -> 966.875 | G28: =+G22*G27/1000000 -> 966.875
B30: IV. COSTOS
B33: Costos (US$ MM) | C33: 0 | D33: 1 | E33: 2 | F33: 3 | G33: 4
B34: Costo Variable (US$/Tn) | D34: =+Principal!$F$18 -> 1980 | E34: =+Principal!$F$18 -> 1980 | F34: =+Principal!$F$18 -> 1980 | G34: =+Principal!$F$18 -> 1980
B36: Costos (US$ MM) | C36: 0 | D36: 1 | E36: 2 | F36: 3 | G36: 4
B37: Costo Variable | D37: =+D22*D34/1000000 -> 420.75 | E37: =+E22*E34/1000000 -> 420.75 | F37: =+F22*F34/1000000 -> 420.75 | G37: =+G22*G34/1000000 -> 420.75
B38: Costo Fijo | D38: =+Principal!$F$19 -> 500 | E38: =+Principal!$F$19 -> 500 | F38: =+Principal!$F$19 -> 500 | G38: =+Principal!$F$19 -> 500
B41: VI. FLUJO DE CAJA OPERATIVO
C43: 0 | D43: 1 | E43: 2 | F43: 3 | G43: 4 | H43: 5 | I43: 6
B44: Ingresos | D44: =+D28 -> 966.875 | E44: =+E28 -> 966.875 | F44: =+F28 -> 966.875 | G44: =+G28 -> 966.875
B45: Costo Variable | D45: =-D37 -> -420.75 | E45: =-E37 -> -420.75 | F45: =-F37 -> -420.75 | G45: =-G37 -> -420.75
B46: Costo Fijo | D46: =-D38 -> -500 | E46: =-E38 -> -500 | F46: =-F38 -> -500 | G46: =-G38 -> -500
B47: Flujo de Caja Op. | D47: =+SUM(D44:D46) -> 46.125 | E47: =+SUM(E44:E46) -> 46.125 | F47: =+SUM(F44:F46) -> 46.125 | G47: =+SUM(G44:G46) -> 46.125 | H47: =+SUM(H44:H46) -> 0 | I47: =+SUM(I44:I46) -> 0
B50: VII. FLUJO DE CAJA ECONÓMICO
C52: 0 | D52: 1 | E52: 2 | F52: 3 | G52: 4 | H52: 5 | I52: 6
B53: Flujo de Caja Op. | D53: =+D47 -> 46.125 | E53: =+E47 -> 46.125 | F53: =+F47 -> 46.125 | G53: =+G47 -> 46.125 | H53: =+H47 -> 0 | I53: =+I47 -> 0
B54: =+B13 -> F. Inversiones | C54: =+C13 -> -165 | D54: =+D13 -> 0 | E54: =+E13 -> 0 | F54: =+F13 -> 0 | G54: =+G13 -> 75 | H54: =+H13 -> -5 | I54: =+I13 -> 20
B55: FCE | C55: =+C54+C53 -> -165 | D55: =+D54+D53 -> 46.125 | E55: =+E54+E53 -> 46.125 | F55: =+F54+F53 -> 46.125 | G55: =+G54+G53 -> 121.125 | H55: =+H54+H53 -> -5 | I55: =+I54+I53 -> 20

Sheet Flujos con Etapas
B2: I. INVERSIONES
B4: Valor Mercado | C4: US$ MM
B5: Terreno | C5: =+Principal!C17 -> 20
B6: Equipos | C6: =+Principal!C16 -> 75
B8: FCI (US$ MM) | C8: 0 | D8: 1 | E8: 2 | F8: 3 | G8: 4 | H8: 5 | I8: 6 | J8: 7 | K8: 8
B9: Terreno | C9: =-Principal!C10 -> -15
B10: Equipo | E10: =+-Principal!C11 -> -150 | I10: =C6 -> 75
B11: Exploración y Factibilidad | D11: =-Principal!C20 -> -10 | E11: =-Principal!C21 -> -10
B12: Restauración_Terreno | J12: =-Principal!C13 -> -5
B13: Valor Venta Terreno | K13: =+C5 -> 20
B14: F. Inversiones | C14: =+SUM(C9:C13) -> -15 | D14: =+SUM(D9:D13) -> -10 | E14: =+SUM(E9:E13) -> -160 | F14: =+SUM(F9:F13) -> 0 | G14: =+SUM(G9:G13) -> 0 | H14: =+SUM(H9:H13) -> 0 | I14: =+SUM(I9:I13) -> 75 | J14: =+SUM(J9:J13) -> -5 | K14: =+SUM(K9:K13) -> 20
B16: II. PRODUCCIÓN
B18: Volumen Reservas | C18: =+Principal!F15 -> 850000
C21: 0 | D21: 1 | E21: 2 | F21: 3 | G21: 4 | H21: 5 | I21: 6
B22: % Mineral vendido | F22: =+Principal!$F$9 -> 0.25 | G22: =+Principal!$F$10 -> 0.25 | H22: =+Principal!$F$11 -> 0.25 | I22: =+Principal!$F$12 -> 0.25
B23: Producción (Tn) | F23: =+F22*$C$18 -> 212500 | G23: =+G22*$C$18 -> 212500 | H23: =+H22*$C$18 -> 212500 | I23: =+I22*$C$18 -> 212500
B25: III. INGRESOS
B27: Ingresos (US$ MM) | C27: 0 | D27: 1 | E27: 2 | F27: 3 | G27: 4 | H27: 5 | I27: 6
B28: Precio (US$/Tn) | C28: =+Principal!$F$7 -> 4550 | D28: =+Principal!$F$7 -> 4550 | E28: =+Principal!$F$7 -> 4550 | F28: =+Principal!$F$7 -> 4550 | G28: =+Principal!$F$7 -> 4550 | H28: =+Principal!$F$7 -> 4550 | I28: =+Principal!$F$7 -> 4550
B29: Total Ingresos | F29: =+F23*F28/1000000 -> 966.875 | G29: =+G23*G28/1000000 -> 966.875 | H29: =+H23*H28/1000000 -> 966.875 | I29: =+I23*I28/1000000 -> 966.875
B31: IV. COSTOS
B34: Costos (US$ MM) | C34: 0 | D34: 1 | E34: 2 | F34: 3 | G34: 4 | H34: 5 | I34: 6
B35: Costo Variable (US$/Tn) | F35: =+Principal!$F$18 -> 1980 | G35: =+Principal!$F$18 -> 1980 | H35: =+Principal!$F$18 -> 1980 | I35: =+Principal!$F$18 -> 1980
B37: Costos (US$ MM) | C37: 0 | D37: 1 | E37: 2 | F37: 3 | G37: 4 | H37: 5 | I37: 6
B38: Costo Variable | F38: =+F23*F35/1000000 -> 420.75 | G38: =+G23*G35/1000000 -> 420.75 | H38: =+H23*H35/1000000 -> 420.75 | I38: =+I23*I35/1000000 -> 420.75
B39: Costo Fijo | F39: =+Principal!$F$19 -> 500 | G39: =+Principal!$F$19 -> 500 | H39: =+Principal!$F$19 -> 500 | I39: =+Principal!$F$19 -> 500
B42: VI. FLUJO DE CAJA OPERATIVO
C44: 0 | D44: 1 | E44: 2 | F44: 3 | G44: 4 | H44: 5 | I44: 6 | J44: 7 | K44: 8
B45: Ingresos | F45: =+F29 -> 966.875 | G45: =+G29 -> 966.875 | H45: =+H29 -> 966.875 | I45: =+I29 -> 966.875
B46: Costo Variable | F46: =-F38 -> -420.75 | G46: =-G38 -> -420.75 | H46: =-H38 -> -420.75 | I46: =-I38 -> -420.75
B47: Costo Fijo | F47: =-F39 -> -500 | G47: =-G39 -> -500 | H47: =-H39 -> -500 | I47: =-I39 -> -500
B48: Flujo de Caja Op. | F48: =+SUM(F45:F47) -> 46.125 | G48: =+SUM(G45:G47) -> 46.125 | H48: =+SUM(H45:H47) -> 46.125 | I48: =+SUM(I45:I47) -> 46.125 | J48: =+SUM(J45:J47) -> 0 | K48: =+SUM(K45:K47) -> 0
B51: VII. FLUJO DE CAJA ECONÓMICO
C53: 0 | D53: 1 | E53: 2 | F53: 3 | G53: 4 | H53: 5 | I53: 6 | J53: 7 | K53: 8
B54: Flujo de Caja Op. | D54: =+D48 -> 0 | E54: =+E48 -> 0 | F54: =+F48 -> 46.125 | G54: =+G48 -> 46.125 | H54: =+H48 -> 46.125 | I54: =+I48 -> 46.125 | J54: =+J48 -> 0 | K54: =+K48 -> 0
B55: =+B14 -> F. Inversiones | C55: =+C14 -> -15 | D55: =+D14 -> -10 | E55: =+E14 -> -160 | F55: =+F14 -> 0 | G55: =+G14 -> 0 | H55: =+H14 -> 0 | I55: =+I14 -> 75 | ... K55: =+K14 -> 20
B56: FCE | C56: =+C55+C54 -> -15 | D56: =+D55+D54 -> -10 | E56: =+E55+E54 -> -160 | F56: =+F55+F54 -> 46.125 | G56: =+G55+G54 -> 46.125 | H56: =+H55+H54 -> 46.125 | I56: =+I55+I54 -> 121.125 | J56: =+J55+J54 -> -5 | K56: =+K55+K54 -> 20
